JINGKE2/__init__.py
JINGKE2/main.py
JINGKE2/test.py
JINGKE2/utils/API.py
JINGKE2/utils/__init__.py
JINGKE2/utils/codeeditor.py
JINGKE2/utils/external.py
JINGKE2/utils/generate.py
JINGKE2/utils/git.py
JINGKE2/utils/manageenv.py
JINGKE2/utils/user.py
JINGKE2/utils/Code/__init__.py
JINGKE2/utils/Code/coderunner.py
JINGKE2/utils/test/__init__.py
JINGKE2/utils/test/fixissues.py
jingke-1.1.6.dist-info/METADATA
jingke-1.1.6.dist-info/WHEEL
jingke-1.1.6.dist-info/entry_points.txt
jingke-1.1.6.dist-info/top_level.txt
jingke-1.1.6.dist-info/RECORD
