Metadata-Version: 2.4
Name: jingke
Version: 1.1.6
Summary: A Python Developer, Used to generate, debug and upload the code in GITHUB.
Author: R Kiran Kumar Reddy
Author-email: ki2003167@gmail.com
Classifier: Programming Language :: Python :: 3
Classifier: License :: OSI Approved :: MIT License
Classifier: Operating System :: Microsoft :: Windows
Requires-Python: >=3.10
Requires-Dist: aiohappyeyeballs==2.6.1
Requires-Dist: aiohttp==3.11.14
Requires-Dist: aiosignal==1.3.2
Requires-Dist: annotated-types==0.7.0
Requires-Dist: ansicon==1.89.0
Requires-Dist: ansiwrap==0.8.4
Requires-Dist: anyio==4.9.0
Requires-Dist: art==6.4
Requires-Dist: asttokens==3.0.0
Requires-Dist: attrs==25.3.0
Requires-Dist: blessed==1.20.0
Requires-Dist: certifi==2025.1.31
Requires-Dist: charset-normalizer==3.4.1
Requires-Dist: click==8.1.8
Requires-Dist: colorama==0.4.6
Requires-Dist: comm==0.2.2
Requires-Dist: console-menu==0.8.0
Requires-Dist: dataclasses-json==0.6.7
Requires-Dist: debugpy==1.8.13
Requires-Dist: decorator==5.2.1
Requires-Dist: distro==1.9.0
Requires-Dist: editor==1.6.6
Requires-Dist: executing==2.2.0
Requires-Dist: frozenlist==1.5.0
Requires-Dist: gitdb==4.0.12
Requires-Dist: GitPython==3.1.44
Requires-Dist: greenlet==3.1.1
Requires-Dist: groq==0.19.0
Requires-Dist: h11==0.14.0
Requires-Dist: httpcore==1.0.7
Requires-Dist: httpx==0.28.1
Requires-Dist: httpx-sse==0.4.0
Requires-Dist: idna==3.10
Requires-Dist: inquirer==3.4.0
Requires-Dist: ipykernel==6.29.5
Requires-Dist: ipython==9.0.2
Requires-Dist: ipython_pygments_lexers==1.1.1
Requires-Dist: jaraco.classes==3.4.0
Requires-Dist: jaraco.context==6.0.1
Requires-Dist: jaraco.functools==4.1.0
Requires-Dist: jedi==0.19.2
Requires-Dist: jinxed==1.3.0
Requires-Dist: joblib==1.4.2
Requires-Dist: jsonpatch==1.33
Requires-Dist: jsonpointer==3.0.0
Requires-Dist: jupyter_client==8.6.3
Requires-Dist: jupyter_core==5.7.2
Requires-Dist: keyboard==0.13.5
Requires-Dist: keyring==25.6.0
Requires-Dist: langchain==0.3.20
Requires-Dist: langchain-community==0.3.19
Requires-Dist: langchain-core==0.3.45
Requires-Dist: langchain-groq==0.2.5
Requires-Dist: langchain-ollama==0.2.3
Requires-Dist: langchain-text-splitters==0.3.6
Requires-Dist: langsmith==0.3.15
Requires-Dist: markdown-it-py==3.0.0
Requires-Dist: marshmallow==3.26.1
Requires-Dist: matplotlib-inline==0.1.7
Requires-Dist: mdurl==0.1.2
Requires-Dist: more-itertools==10.6.0
Requires-Dist: multidict==6.2.0
Requires-Dist: mypy-extensions==1.0.0
Requires-Dist: nest-asyncio==1.6.0
Requires-Dist: numpy==2.2.4
Requires-Dist: ollama==0.4.7
Requires-Dist: orjson==3.10.15
Requires-Dist: packaging==24.2
Requires-Dist: parso==0.8.4
Requires-Dist: Pillow==9.5.0
Requires-Dist: platformdirs==4.3.7
Requires-Dist: prompt_toolkit==3.0.50
Requires-Dist: propcache==0.3.0
Requires-Dist: psutil==7.0.0
Requires-Dist: pure_eval==0.2.3
Requires-Dist: pydantic==2.10.6
Requires-Dist: pydantic-settings==2.8.1
Requires-Dist: pydantic_core==2.27.2
Requires-Dist: Pygments==2.19.1
Requires-Dist: python-dateutil==2.9.0.post0
Requires-Dist: python-dotenv==1.0.1
Requires-Dist: pytz==2025.2
Requires-Dist: pywin32==310
Requires-Dist: pywin32-ctypes==0.2.3
Requires-Dist: PyYAML==6.0.2
Requires-Dist: pyzmq==26.3.0
Requires-Dist: readchar==4.2.1
Requires-Dist: requests==2.32.3
Requires-Dist: requests-toolbelt==1.0.0
Requires-Dist: rich==13.9.4
Requires-Dist: runs==1.2.2
Requires-Dist: scikit-learn==1.6.1
Requires-Dist: scipy==1.15.2
Requires-Dist: simple-term-menu==1.6.6
Requires-Dist: six==1.17.0
Requires-Dist: smmap==5.0.2
Requires-Dist: sniffio==1.3.1
Requires-Dist: SQLAlchemy==2.0.39
Requires-Dist: stack-data==0.6.3
Requires-Dist: tenacity==9.0.0
Requires-Dist: textwrap3==0.9.2
Requires-Dist: threadpoolctl==3.6.0
Requires-Dist: tornado==6.4.2
Requires-Dist: traitlets==5.14.3
Requires-Dist: typing-inspect==0.9.0
Requires-Dist: typing_extensions==4.12.2
Requires-Dist: tzdata==2025.2
Requires-Dist: urllib3==2.3.0
Requires-Dist: wcwidth==0.2.13
Requires-Dist: xmod==1.8.1
Requires-Dist: yarl==1.18.3
Requires-Dist: zstandard==0.23.0
Dynamic: author
Dynamic: author-email
Dynamic: classifier
Dynamic: description
Dynamic: description-content-type
Dynamic: requires-dist
Dynamic: requires-python
Dynamic: summary
